distributions/Binomialdistribution.py
distributions/Gaussiandistribution.py
distributions/Generaldistribution.py
distributions/__init__.py
stest_distributions-0.1.dist-info/DESCRIPTION.rst
stest_distributions-0.1.dist-info/METADATA
stest_distributions-0.1.dist-info/RECORD
stest_distributions-0.1.dist-info/WHEEL
stest_distributions-0.1.dist-info/metadata.json
stest_distributions-0.1.dist-info/top_level.txt
